yava247ai/__init__.py
yava247ai/experiment.py
yava247ai/experiment_2.py
yava247ai-0.0.2.dist-info/METADATA
yava247ai-0.0.2.dist-info/WHEEL
yava247ai-0.0.2.dist-info/top_level.txt
yava247ai-0.0.2.dist-info/RECORD
