Metadata-Version: 2.1
Name: yava247ai
Version: 0.0.2
Summary: Experiment for tracking
Author: Ahmad Lutfi Bayu Aji of Labs247
Requires-Dist: scikit-learn
Requires-Dist: mlflow
Requires-Dist: pyarrow
